bmmltools/__init__.py
bmmltools/run_bmmlboard.py
bmmltools/board/__init__.py
bmmltools/board/graph.html
bmmltools/board/home.py
bmmltools/board/backend/__init__.py
bmmltools/board/backend/tracegraph.py
bmmltools/board/backend/visualization.py
bmmltools/board/visualization_app/__init__.py
bmmltools/board/visualization_app/explainer_visualizer.py
bmmltools/board/visualization_app/label_visualizer.py
bmmltools/board/visualization_app/segmentation_visualizer.py
bmmltools/core/__init__.py
bmmltools/core/data.py
bmmltools/core/tracer.py
bmmltools/features/__init__.py
bmmltools/features/dft.py
bmmltools/features/dish.py
bmmltools/operations/__init__.py
bmmltools/operations/clustering.py
bmmltools/operations/explanation.py
bmmltools/operations/feature.py
bmmltools/operations/io.py
bmmltools/operations/segmentation.py
bmmltools/utils/__init__.py
bmmltools/utils/basic.py
bmmltools/utils/geometric.py
bmmltools/utils/graph.py
bmmltools/utils/io_utils.py
bmmltools-0.2.8.dist-info/LICENSE
bmmltools-0.2.8.dist-info/METADATA
bmmltools-0.2.8.dist-info/WHEEL
bmmltools-0.2.8.dist-info/top_level.txt
bmmltools-0.2.8.dist-info/RECORD
